{
  "trade_pairs": [
    {
      "entry_date": "2020-03-06",
      "entry_price": 1358.800048828125,
      "exit_date": "2020-03-09",
      "exit_price": 1299.0,
      "position_type": "SHORT",
      "quantity": 100,
      "pnl": 5980,
      "entry_rci": -96.66666666666666,
      "entry_adx": 32.0457132006025,
      "signal_reason": "RCI-:SELL(strength=96.7, +DI=15.9, -DI=44.4)",
      "exit_reason": "利益目標額達成(5980円)"
    },
    {
      "entry_date": "2020-03-10",
      "entry_price": 1320.0,
      "exit_date": "2020-03-12",
      "exit_price": 1261.800048828125,
      "position_type": "SHORT",
      "quantity": 100,
      "pnl": 5820,
      "entry_rci": -95.0,
      "entry_adx": 38.81954452082141,
      "signal_reason": "RCI-:SELL(strength=95.0, +DI=12.3, -DI=47.4)",
      "exit_reason": "利益目標額達成(5820円)"
    },
    {
      "entry_date": "2020-03-13",
      "entry_price": 1216.800048828125,
      "exit_date": "2020-03-17",
      "exit_price": 1272.0,
      "position_type": "SHORT",
      "quantity": 100,
      "pnl": -5520,
      "entry_rci": -93.33333333333333,
      "entry_adx": 49.33772430959163,
      "signal_reason": "RCI-:SELL(strength=93.3, +DI=13.3, -DI=52.1)",
      "exit_reason": "stop_loss"
    },
    {
      "entry_date": "2020-03-18",
      "entry_price": 1263.4000244140625,
      "exit_date": "2020-03-19",
      "exit_price": 1279.0,
      "position_type": "SHORT",
      "quantity": 100,
      "pnl": -1560,
      "entry_rci": -70.0,
      "entry_adx": 58.378494031069636,
      "signal_reason": "RCI-:SELL(strength=70.0, +DI=23.1, -DI=35.8)",
      "exit_reason": "トレーリングストップ(4.0%)"
    },
    {
      "entry_date": "2020-06-08",
      "entry_price": 1433.4000244140625,
      "exit_date": "2020-06-11",
      "exit_price": 1381.0,
      "position_type": "LONG",
      "quantity": 100,
      "pnl": -5240,
      "entry_rci": 76.66666666666666,
      "entry_adx": 30.054582337962994,
      "signal_reason": "RCI+:BUY(strength=76.7, +DI=42.1, -DI=18.6, +DI/-DI=2.26 >= 1.20)",
      "exit_reason": "RCI傾き利確(-30.0度)"
    },
    {
      "entry_date": "2020-08-14",
      "entry_price": 1436.199951171875,
      "exit_date": "2020-08-18",
      "exit_price": 1435.199951171875,
      "position_type": "LONG",
      "quantity": 100,
      "pnl": -100,
      "entry_rci": 95.0,
      "entry_adx": 30.562083655552875,
      "signal_reason": "RCI+:BUY(strength=95.0, +DI=42.7, -DI=22.7, +DI/-DI=1.88 >= 1.20)",
      "exit_reason": "RCI傾き利確(-13.5度)"
    },
    {
      "entry_date": "2020-08-19",
      "entry_price": 1439.0,
      "exit_date": "2020-08-20",
      "exit_price": 1416.800048828125,
      "position_type": "LONG",
      "quantity": 100,
      "pnl": -2220,
      "entry_rci": 55.00000000000001,
      "entry_adx": 30.845605696046125,
      "signal_reason": "RCI+:BUY(strength=55.0, +DI=36.2, -DI=24.3, +DI/-DI=1.49 >= 1.20)",
      "exit_reason": "RCI傾き利確(-42.0度)"
    },
    {
      "entry_date": "2020-11-27",
      "entry_price": 1450.4000244140625,
      "exit_date": "2020-11-30",
      "exit_price": 1399.800048828125,
      "position_type": "SHORT",
      "quantity": 100,
      "pnl": 5060,
      "entry_rci": -66.66666666666667,
      "entry_adx": 34.75997413795485,
      "signal_reason": "RCI-:SELL(strength=66.7, +DI=24.0, -DI=24.2)",
      "exit_reason": "利益目標額達成(5060円)"
    },
    {
      "entry_date": "2020-12-01",
      "entry_price": 1403.5999755859375,
      "exit_date": "2020-12-04",
      "exit_price": 1436.199951171875,
      "position_type": "SHORT",
      "quantity": 100,
      "pnl": -3260,
      "entry_rci": -64.99999999999999,
      "entry_adx": 32.651577147725035,
      "signal_reason": "RCI-:SELL(strength=65.0, +DI=19.9, -DI=28.9)",
      "exit_reason": "RCI傾き利確(13.5度)"
    },
    {
      "entry_date": "2020-12-09",
      "entry_price": 1469.800048828125,
      "exit_date": "2020-12-11",
      "exit_price": 1564.0,
      "position_type": "LONG",
      "quantity": 100,
      "pnl": 9420,
      "entry_rci": 51.66666666666666,
      "entry_adx": 31.321302683666694,
      "signal_reason": "RCI+:BUY(strength=51.7, +DI=26.3, -DI=20.5, +DI/-DI=1.29 >= 1.20)",
      "exit_reason": "利益目標額達成(9420円)"
    },
    {
      "entry_date": "2020-12-16",
      "entry_price": 1596.0,
      "exit_date": "2020-12-21",
      "exit_price": 1570.0,
      "position_type": "LONG",
      "quantity": 100,
      "pnl": -2600,
      "entry_rci": 96.66666666666667,
      "entry_adx": 30.920166765334617,
      "signal_reason": "RCI+:BUY(strength=96.7, +DI=43.3, -DI=13.3, +DI/-DI=3.25 >= 1.20)",
      "exit_reason": "RCI傾き利確(-22.5度)"
    },
    {
      "entry_date": "2021-01-04",
      "entry_price": 1585.5999755859375,
      "exit_date": "2021-01-06",
      "exit_price": 1563.5999755859375,
      "position_type": "LONG",
      "quantity": 100,
      "pnl": -2200,
      "entry_rci": 71.66666666666667,
      "entry_adx": 49.18624033964956,
      "signal_reason": "RCI+:BUY(strength=71.7, +DI=32.5, -DI=20.0, +DI/-DI=1.63 >= 1.20)",
      "exit_reason": "RCI傾き利確(-16.5度)"
    },
    {
      "entry_date": "2021-01-28",
      "entry_price": 1479.4000244140625,
      "exit_date": "2021-02-03",
      "exit_price": 1556.4000244140625,
      "position_type": "SHORT",
      "quantity": 100,
      "pnl": -7700,
      "entry_rci": -66.66666666666667,
      "entry_adx": 30.213245544432745,
      "signal_reason": "RCI-:SELL(strength=66.7, +DI=11.0, -DI=40.5)",
      "exit_reason": "stop_loss"
    },
    {
      "entry_date": "2021-02-05",
      "entry_price": 1584.4000244140625,
      "exit_date": "2021-02-12",
      "exit_price": 1682.5999755859375,
      "position_type": "LONG",
      "quantity": 100,
      "pnl": 9820,
      "entry_rci": 51.66666666666666,
      "entry_adx": 41.79372475242179,
      "signal_reason": "RCI+:BUY(strength=51.7, +DI=36.1, -DI=22.4, +DI/-DI=1.61 >= 1.20)",
      "exit_reason": "利益目標額達成(9820円)"
    },
    {
      "entry_date": "2021-02-15",
      "entry_price": 1691.199951171875,
      "exit_date": "2021-02-18",
      "exit_price": 1618.5999755859375,
      "position_type": "LONG",
      "quantity": 100,
      "pnl": -7260,
      "entry_rci": 96.66666666666667,
      "entry_adx": 39.324176853788,
      "signal_reason": "RCI+:BUY(strength=96.7, +DI=38.4, -DI=16.4, +DI/-DI=2.35 >= 1.20)",
      "exit_reason": "stop_loss"
    },
    {
      "entry_date": "2021-02-24",
      "entry_price": 1578.199951171875,
      "exit_date": "2021-03-03",
      "exit_price": 1594.199951171875,
      "position_type": "SHORT",
      "quantity": 100,
      "pnl": -1600,
      "entry_rci": -81.66666666666667,
      "entry_adx": 32.05929961068152,
      "signal_reason": "RCI-:SELL(strength=81.7, +DI=27.6, -DI=30.1)",
      "exit_reason": "RCI傾き利確(16.5度)"
    },
    {
      "entry_date": "2021-05-31",
      "entry_price": 1823.0,
      "exit_date": "2021-06-01",
      "exit_price": 1884.5999755859375,
      "position_type": "LONG",
      "quantity": 100,
      "pnl": 6160,
      "entry_rci": 96.66666666666667,
      "entry_adx": 31.96482896366003,
      "signal_reason": "RCI+:BUY(strength=96.7, +DI=36.4, -DI=15.4, +DI/-DI=2.36 >= 1.20)",
      "exit_reason": "利益目標額達成(6160円)"
    },
    {
      "entry_date": "2021-06-02",
      "entry_price": 1925.5999755859375,
      "exit_date": "2021-06-04",
      "exit_price": 1989.800048828125,
      "position_type": "LONG",
      "quantity": 100,
      "pnl": 6420,
      "entry_rci": 98.33333333333333,
      "entry_adx": 40.367805084714476,
      "signal_reason": "RCI+:BUY(strength=98.3, +DI=45.2, -DI=12.8, +DI/-DI=3.54 >= 1.20)",
      "exit_reason": "利益目標額達成(6420円)"
    },
    {
      "entry_date": "2021-06-07",
      "entry_price": 1983.4000244140625,
      "exit_date": "2021-06-10",
      "exit_price": 1973.199951171875,
      "position_type": "LONG",
      "quantity": 100,
      "pnl": -1020,
      "entry_rci": 96.66666666666667,
      "entry_adx": 56.04536796982614,
      "signal_reason": "RCI+:BUY(strength=96.7, +DI=46.8, -DI=8.0, +DI/-DI=5.86 >= 1.20)",
      "exit_reason": "RCI傾き利確(-10.5度)"
    },
    {
      "entry_date": "2021-06-11",
      "entry_price": 1972.199951171875,
      "exit_date": "2021-06-14",
      "exit_price": 1980.0,
      "position_type": "LONG",
      "quantity": 100,
      "pnl": 780,
      "entry_rci": 51.66666666666666,
      "entry_adx": 72.84798920197629,
      "signal_reason": "RCI+:BUY(strength=51.7, +DI=39.6, -DI=10.2, +DI/-DI=3.87 >= 1.20)",
      "exit_reason": "RCI傾き利確(-21.0度)"
    },
    {
      "entry_date": "2021-06-17",
      "entry_price": 2046.0,
      "exit_date": "2021-06-18",
      "exit_price": 1966.5999755859375,
      "position_type": "LONG",
      "quantity": 100,
      "pnl": -7940,
      "entry_rci": 63.33333333333333,
      "entry_adx": 83.47651608423583,
      "signal_reason": "RCI+:BUY(strength=63.3, +DI=44.8, -DI=7.9, +DI/-DI=5.64 >= 1.20)",
      "exit_reason": "RCI傾き利確(-31.5度)"
    },
    {
      "entry_date": "2021-08-25",
      "entry_price": 1896.800048828125,
      "exit_date": "2021-08-26",
      "exit_price": 1901.4000244140625,
      "position_type": "SHORT",
      "quantity": 100,
      "pnl": -460,
      "entry_rci": -76.66666666666666,
      "entry_adx": 30.758200646396393,
      "signal_reason": "RCI-:SELL(strength=76.7, +DI=20.8, -DI=37.3)",
      "exit_reason": "RCI傾き利確(22.5度)"
    },
    {
      "entry_date": "2021-09-06",
      "entry_price": 1992.4000244140625,
      "exit_date": "2021-09-10",
      "exit_price": 1991.800048828125,
      "position_type": "LONG",
      "quantity": 100,
      "pnl": -60,
      "entry_rci": 93.33333333333333,
      "entry_adx": 44.02622227710446,
      "signal_reason": "RCI+:BUY(strength=93.3, +DI=32.4, -DI=26.6, +DI/-DI=1.22 >= 1.20)",
      "exit_reason": "RCI傾き利確(-13.5度)"
    },
    {
      "entry_date": "2021-09-27",
      "entry_price": 2066.0,
      "exit_date": "2021-09-30",
      "exit_price": 2000.0,
      "position_type": "LONG",
      "quantity": 100,
      "pnl": -6600,
      "entry_rci": 58.33333333333333,
      "entry_adx": 36.518658364360434,
      "signal_reason": "RCI+:BUY(strength=58.3, +DI=38.8, -DI=24.5, +DI/-DI=1.58 >= 1.20)",
      "exit_reason": "RCI傾き利確(-19.5度)"
    },
    {
      "entry_date": "2021-11-19",
      "entry_price": 2132.5,
      "exit_date": "2021-11-22",
      "exit_price": 2105.0,
      "position_type": "LONG",
      "quantity": 100,
      "pnl": -2750,
      "entry_rci": 88.33333333333333,
      "entry_adx": 31.580100881978957,
      "signal_reason": "RCI+:BUY(strength=88.3, +DI=36.6, -DI=17.4, +DI/-DI=2.10 >= 1.20)",
      "exit_reason": "RCI傾き利確(-15.0度)"
    },
    {
      "entry_date": "2021-11-24",
      "entry_price": 2124.5,
      "exit_date": "2021-11-25",
      "exit_price": 2112.0,
      "position_type": "LONG",
      "quantity": 100,
      "pnl": -1250,
      "entry_rci": 53.333333333333336,
      "entry_adx": 38.796473158056656,
      "signal_reason": "RCI+:BUY(strength=53.3, +DI=35.5, -DI=16.0, +DI/-DI=2.22 >= 1.20)",
      "exit_reason": "RCI傾き利確(-28.5度)"
    },
    {
      "entry_date": "2021-11-29",
      "entry_price": 2012.0,
      "exit_date": "2021-12-03",
      "exit_price": 2079.0,
      "position_type": "SHORT",
      "quantity": 100,
      "pnl": -6700,
      "entry_rci": -85.00000000000001,
      "entry_adx": 40.510821210472876,
      "signal_reason": "RCI-:SELL(strength=85.0, +DI=25.7, -DI=29.8)",
      "exit_reason": "RCI傾き利確(22.5度)"
    },
    {
      "entry_date": "2022-01-14",
      "entry_price": 2390.0,
      "exit_date": "2022-01-19",
      "exit_price": 2303.0,
      "position_type": "LONG",
      "quantity": 100,
      "pnl": -8700,
      "entry_rci": 96.66666666666667,
      "entry_adx": 32.72192579417343,
      "signal_reason": "RCI+:BUY(strength=96.7, +DI=43.1, -DI=10.8, +DI/-DI=3.99 >= 1.20)",
      "exit_reason": "トレーリングストップ(4.0%)"
    },
    {
      "entry_date": "2022-01-27",
      "entry_price": 2163.0,
      "exit_date": "2022-01-31",
      "exit_price": 2245.5,
      "position_type": "SHORT",
      "quantity": 100,
      "pnl": -8250,
      "entry_rci": -96.66666666666666,
      "entry_adx": 50.38337681637402,
      "signal_reason": "RCI-:SELL(strength=96.7, +DI=20.7, -DI=26.3)",
      "exit_reason": "RCI傾き利確(15.0度)"
    },
    {
      "entry_date": "2022-02-04",
      "entry_price": 2277.5,
      "exit_date": "2022-02-10",
      "exit_price": 2254.0,
      "position_type": "LONG",
      "quantity": 100,
      "pnl": -2350,
      "entry_rci": 78.33333333333333,
      "entry_adx": 36.42384834016597,
      "signal_reason": "RCI+:BUY(strength=78.3, +DI=22.4, -DI=14.5, +DI/-DI=1.55 >= 1.20)",
      "exit_reason": "RCI傾き利確(-28.5度)"
    },
    {
      "entry_date": "2022-03-08",
      "entry_price": 1811.0,
      "exit_date": "2022-03-10",
      "exit_price": 1945.5,
      "position_type": "SHORT",
      "quantity": 100,
      "pnl": -13450,
      "entry_rci": -83.33333333333333,
      "entry_adx": 32.47929986079064,
      "signal_reason": "RCI-:SELL(strength=83.3, +DI=11.3, -DI=44.3)",
      "exit_reason": "stop_loss"
    },
    {
      "entry_date": "2022-03-11",
      "entry_price": 1860.5,
      "exit_date": "2022-03-14",
      "exit_price": 1914.0,
      "position_type": "SHORT",
      "quantity": 100,
      "pnl": -5350,
      "entry_rci": -68.33333333333333,
      "entry_adx": 42.196299776011145,
      "signal_reason": "RCI-:SELL(strength=68.3, +DI=18.0, -DI=38.9)",
      "exit_reason": "RCI傾き利確(19.5度)"
    },
    {
      "entry_date": "2022-03-23",
      "entry_price": 2137.0,
      "exit_date": "2022-03-24",
      "exit_price": 2200.0,
      "position_type": "LONG",
      "quantity": 100,
      "pnl": 6300,
      "entry_rci": 93.33333333333333,
      "entry_adx": 40.21184302226198,
      "signal_reason": "RCI+:BUY(strength=93.3, +DI=35.5, -DI=28.8, +DI/-DI=1.24 >= 1.20)",
      "exit_reason": "利益目標額達成(6300円)"
    },
    {
      "entry_date": "2022-03-25",
      "entry_price": 2189.0,
      "exit_date": "2022-03-29",
      "exit_price": 2261.0,
      "position_type": "LONG",
      "quantity": 100,
      "pnl": 7200,
      "entry_rci": 96.66666666666667,
      "entry_adx": 34.746882772749416,
      "signal_reason": "RCI+:BUY(strength=96.7, +DI=38.7, -DI=24.7, +DI/-DI=1.57 >= 1.20)",
      "exit_reason": "利益目標額達成(7200円)"
    },
    {
      "entry_date": "2022-03-30",
      "entry_price": 2218.5,
      "exit_date": "2022-04-04",
      "exit_price": 2211.0,
      "position_type": "LONG",
      "quantity": 100,
      "pnl": -750,
      "entry_rci": 95.0,
      "entry_adx": 34.88185998658876,
      "signal_reason": "RCI+:BUY(strength=95.0, +DI=36.7, -DI=24.3, +DI/-DI=1.51 >= 1.20)",
      "exit_reason": "RCI傾き利確(-13.5度)"
    },
    {
      "entry_date": "2022-04-08",
      "entry_price": 2095.5,
      "exit_date": "2022-04-14",
      "exit_price": 2131.5,
      "position_type": "SHORT",
      "quantity": 100,
      "pnl": -3600,
      "entry_rci": -91.66666666666667,
      "entry_adx": 47.44529198439238,
      "signal_reason": "RCI-:SELL(strength=91.7, +DI=26.6, -DI=33.5)",
      "exit_reason": "RCI傾き利確(10.5度)"
    },
    {
      "entry_date": "2022-04-20",
      "entry_price": 2258.5,
      "exit_date": "2022-04-26",
      "exit_price": 2180.0,
      "position_type": "LONG",
      "quantity": 100,
      "pnl": -7850,
      "entry_rci": 93.33333333333333,
      "entry_adx": 35.082672687830126,
      "signal_reason": "RCI+:BUY(strength=93.3, +DI=38.4, -DI=15.0, +DI/-DI=2.55 >= 1.20)",
      "exit_reason": "RCI傾き利確(-15.0度)"
    },
    {
      "entry_date": "2022-05-19",
      "entry_price": 2005.0,
      "exit_date": "2022-05-23",
      "exit_price": 2061.5,
      "position_type": "SHORT",
      "quantity": 100,
      "pnl": -5650,
      "entry_rci": -96.66666666666666,
      "entry_adx": 30.230656663343808,
      "signal_reason": "RCI-:SELL(strength=96.7, +DI=15.1, -DI=37.3)",
      "exit_reason": "RCI傾き利確(42.0度)"
    },
    {
      "entry_date": "2022-06-01",
      "entry_price": 2197.5,
      "exit_date": "2022-06-07",
      "exit_price": 2190.5,
      "position_type": "LONG",
      "quantity": 100,
      "pnl": -700,
      "entry_rci": 86.66666666666667,
      "entry_adx": 35.95734783612144,
      "signal_reason": "RCI+:BUY(strength=86.7, +DI=33.9, -DI=22.9, +DI/-DI=1.48 >= 1.20)",
      "exit_reason": "RCI傾き利確(-10.5度)"
    },
    {
      "entry_date": "2022-06-08",
      "entry_price": 2230.0,
      "exit_date": "2022-06-13",
      "exit_price": 2131.5,
      "position_type": "LONG",
      "quantity": 100,
      "pnl": -9850,
      "entry_rci": 70.0,
      "entry_adx": 35.61317865317905,
      "signal_reason": "RCI+:BUY(strength=70.0, +DI=32.3, -DI=23.5, +DI/-DI=1.37 >= 1.20)",
      "exit_reason": "stop_loss"
    },
    {
      "entry_date": "2022-09-21",
      "entry_price": 2000.0,
      "exit_date": "2022-09-30",
      "exit_price": 1876.0,
      "position_type": "SHORT",
      "quantity": 100,
      "pnl": 12400,
      "entry_rci": -88.33333333333333,
      "entry_adx": 36.54167653085283,
      "signal_reason": "RCI-:SELL(strength=88.3, +DI=22.6, -DI=34.4)",
      "exit_reason": "利益目標額達成(12400円)"
    },
    {
      "entry_date": "2022-10-03",
      "entry_price": 1941.5,
      "exit_date": "2022-10-04",
      "exit_price": 2004.0,
      "position_type": "SHORT",
      "quantity": 100,
      "pnl": -6250,
      "entry_rci": -93.33333333333333,
      "entry_adx": 33.861811761351,
      "signal_reason": "RCI-:SELL(strength=93.3, +DI=11.8, -DI=38.7)",
      "exit_reason": "RCI傾き利確(43.5度)"
    },
    {
      "entry_date": "2022-12-21",
      "entry_price": 1808.0,
      "exit_date": "2022-12-28",
      "exit_price": 1819.0,
      "position_type": "SHORT",
      "quantity": 100,
      "pnl": -1100,
      "entry_rci": -66.66666666666667,
      "entry_adx": 33.61163013377833,
      "signal_reason": "RCI-:SELL(strength=66.7, +DI=15.8, -DI=50.4)",
      "exit_reason": "RCI傾き利確(13.5度)"
    },
    {
      "entry_date": "2022-12-29",
      "entry_price": 1817.0,
      "exit_date": "2022-12-30",
      "exit_price": 1812.5,
      "position_type": "SHORT",
      "quantity": 100,
      "pnl": 450,
      "entry_rci": -56.666666666666664,
      "entry_adx": 46.615919981925934,
      "signal_reason": "RCI-:SELL(strength=56.7, +DI=15.6, -DI=45.1)",
      "exit_reason": "RCI傾き利確(10.5度)"
    },
    {
      "entry_date": "2023-01-05",
      "entry_price": 1807.5,
      "exit_date": "2023-01-06",
      "exit_price": 1825.0,
      "position_type": "SHORT",
      "quantity": 100,
      "pnl": -1750,
      "entry_rci": -89.99999999999999,
      "entry_adx": 53.13848483435508,
      "signal_reason": "RCI-:SELL(strength=90.0, +DI=17.0, -DI=45.5)",
      "exit_reason": "RCI傾き利確(54.0度)"
    },
    {
      "entry_date": "2023-01-18",
      "entry_price": 1909.5,
      "exit_date": "2023-01-26",
      "exit_price": 1893.0,
      "position_type": "LONG",
      "quantity": 100,
      "pnl": -1650,
      "entry_rci": 60.0,
      "entry_adx": 38.975500467381764,
      "signal_reason": "RCI+:BUY(strength=60.0, +DI=37.5, -DI=28.8, +DI/-DI=1.30 >= 1.20)",
      "exit_reason": "RCI傾き利確(-13.5度)"
    },
    {
      "entry_date": "2023-01-31",
      "entry_price": 1896.5,
      "exit_date": "2023-02-01",
      "exit_price": 1903.0,
      "position_type": "LONG",
      "quantity": 100,
      "pnl": 650,
      "entry_rci": 53.333333333333336,
      "entry_adx": 38.59568400990822,
      "signal_reason": "RCI+:BUY(strength=53.3, +DI=31.2, -DI=23.4, +DI/-DI=1.33 >= 1.20)",
      "exit_reason": "RCI傾き利確(-16.5度)"
    },
    {
      "entry_date": "2023-05-12",
      "entry_price": 1942.0,
      "exit_date": "2023-05-17",
      "exit_price": 1928.0,
      "position_type": "LONG",
      "quantity": 100,
      "pnl": -1400,
      "entry_rci": 83.33333333333334,
      "entry_adx": 33.002622072470885,
      "signal_reason": "RCI+:BUY(strength=83.3, +DI=35.9, -DI=13.5, +DI/-DI=2.67 >= 1.20)",
      "exit_reason": "RCI傾き利確(-10.5度)"
    },
    {
      "entry_date": "2023-05-18",
      "entry_price": 1955.5,
      "exit_date": "2023-05-23",
      "exit_price": 1857.0,
      "position_type": "LONG",
      "quantity": 100,
      "pnl": -9850,
      "entry_rci": 65.0,
      "entry_adx": 40.80404477896182,
      "signal_reason": "RCI+:BUY(strength=65.0, +DI=34.0, -DI=13.2, +DI/-DI=2.57 >= 1.20)",
      "exit_reason": "stop_loss"
    },
    {
      "entry_date": "2023-05-30",
      "entry_price": 1940.0,
      "exit_date": "2023-06-01",
      "exit_price": 1943.0,
      "position_type": "SHORT",
      "quantity": 100,
      "pnl": -300,
      "entry_rci": -53.33333333333334,
      "entry_adx": 46.43602857602457,
      "signal_reason": "RCI-:SELL(strength=53.3, +DI=17.1, -DI=22.4)",
      "exit_reason": "RCI傾き利確(33.0度)"
    },
    {
      "entry_date": "2023-06-06",
      "entry_price": 2050.0,
      "exit_date": "2023-06-13",
      "exit_price": 2173.5,
      "position_type": "LONG",
      "quantity": 100,
      "pnl": 12350,
      "entry_rci": 76.66666666666666,
      "entry_adx": 32.66071946978464,
      "signal_reason": "RCI+:BUY(strength=76.7, +DI=30.8, -DI=15.9, +DI/-DI=1.94 >= 1.20)",
      "exit_reason": "利益目標額達成(12350円)"
    },
    {
      "entry_date": "2023-06-15",
      "entry_price": 2320.5,
      "exit_date": "2023-06-20",
      "exit_price": 2244.0,
      "position_type": "LONG",
      "quantity": 100,
      "pnl": -7650,
      "entry_rci": 86.66666666666667,
      "entry_adx": 33.80703565881658,
      "signal_reason": "RCI+:BUY(strength=86.7, +DI=50.4, -DI=7.7, +DI/-DI=6.56 >= 1.20)",
      "exit_reason": "RCI傾き利確(-15.0度)"
    },
    {
      "entry_date": "2023-06-30",
      "entry_price": 2308.5,
      "exit_date": "2023-07-07",
      "exit_price": 2299.5,
      "position_type": "LONG",
      "quantity": 100,
      "pnl": -900,
      "entry_rci": 60.0,
      "entry_adx": 56.4907658152202,
      "signal_reason": "RCI+:BUY(strength=60.0, +DI=37.1, -DI=15.1, +DI/-DI=2.46 >= 1.20)",
      "exit_reason": "RCI傾き利確(-33.0度)"
    },
    {
      "entry_date": "2023-08-08",
      "entry_price": 2423.5,
      "exit_date": "2023-08-09",
      "exit_price": 2395.5,
      "position_type": "LONG",
      "quantity": 100,
      "pnl": -2800,
      "entry_rci": 53.333333333333336,
      "entry_adx": 32.408531930784804,
      "signal_reason": "RCI+:BUY(strength=53.3, +DI=34.1, -DI=12.4, +DI/-DI=2.76 >= 1.20)",
      "exit_reason": "RCI傾き利確(-30.0度)"
    },
    {
      "entry_date": "2023-08-28",
      "entry_price": 2436.5,
      "exit_date": "2023-08-31",
      "exit_price": 2515.0,
      "position_type": "LONG",
      "quantity": 100,
      "pnl": 7850,
      "entry_rci": 70.0,
      "entry_adx": 30.303425110127428,
      "signal_reason": "RCI+:BUY(strength=70.0, +DI=35.1, -DI=15.6, +DI/-DI=2.25 >= 1.20)",
      "exit_reason": "利益目標額達成(7850円)"
    },
    {
      "entry_date": "2023-09-07",
      "entry_price": 2637.0,
      "exit_date": "2023-09-11",
      "exit_price": 2595.0,
      "position_type": "LONG",
      "quantity": 100,
      "pnl": -4200,
      "entry_rci": 95.0,
      "entry_adx": 32.08821684171547,
      "signal_reason": "RCI+:BUY(strength=95.0, +DI=44.5, -DI=7.8, +DI/-DI=5.68 >= 1.20)",
      "exit_reason": "RCI傾き利確(-16.5度)"
    },
    {
      "entry_date": "2023-09-12",
      "entry_price": 2657.0,
      "exit_date": "2023-09-13",
      "exit_price": 2707.5,
      "position_type": "LONG",
      "quantity": 100,
      "pnl": 5050,
      "entry_rci": 73.33333333333334,
      "entry_adx": 42.490067309349435,
      "signal_reason": "RCI+:BUY(strength=73.3, +DI=35.8, -DI=14.2, +DI/-DI=2.52 >= 1.20)",
      "exit_reason": "利益目標額達成(5050円)"
    },
    {
      "entry_date": "2023-09-14",
      "entry_price": 2748.0,
      "exit_date": "2023-09-15",
      "exit_price": 2821.5,
      "position_type": "LONG",
      "quantity": 100,
      "pnl": 7350,
      "entry_rci": 73.33333333333334,
      "entry_adx": 51.87426473980677,
      "signal_reason": "RCI+:BUY(strength=73.3, +DI=44.9, -DI=12.2, +DI/-DI=3.68 >= 1.20)",
      "exit_reason": "利益目標額達成(7350円)"
    },
    {
      "entry_date": "2023-09-19",
      "entry_price": 2880.0,
      "exit_date": "2023-09-22",
      "exit_price": 2788.5,
      "position_type": "LONG",
      "quantity": 100,
      "pnl": -9150,
      "entry_rci": 83.33333333333334,
      "entry_adx": 63.173944591378905,
      "signal_reason": "RCI+:BUY(strength=83.3, +DI=50.8, -DI=10.3, +DI/-DI=4.92 >= 1.20)",
      "exit_reason": "RCI傾き利確(-12.0度)"
    },
    {
      "entry_date": "2023-10-04",
      "entry_price": 2477.5,
      "exit_date": "2023-10-05",
      "exit_price": 2590.0,
      "position_type": "SHORT",
      "quantity": 100,
      "pnl": -11250,
      "entry_rci": -96.66666666666666,
      "entry_adx": 51.385899106705956,
      "signal_reason": "RCI-:SELL(strength=96.7, +DI=23.6, -DI=31.6)",
      "exit_reason": "stop_loss"
    },
    {
      "entry_date": "2023-10-06",
      "entry_price": 2572.0,
      "exit_date": "2023-10-10",
      "exit_price": 2624.5,
      "position_type": "SHORT",
      "quantity": 100,
      "pnl": -5250,
      "entry_rci": -91.66666666666667,
      "entry_adx": 44.984400560669194,
      "signal_reason": "RCI-:SELL(strength=91.7, +DI=23.5, -DI=25.7)",
      "exit_reason": "RCI傾き利確(13.5度)"
    },
    {
      "entry_date": "2023-10-13",
      "entry_price": 2687.5,
      "exit_date": "2023-10-18",
      "exit_price": 2669.0,
      "position_type": "LONG",
      "quantity": 100,
      "pnl": -1850,
      "entry_rci": 51.66666666666666,
      "entry_adx": 33.011072498013284,
      "signal_reason": "RCI+:BUY(strength=51.7, +DI=30.6, -DI=19.4, +DI/-DI=1.58 >= 1.20)",
      "exit_reason": "RCI傾き利確(-12.0度)"
    },
    {
      "entry_date": "2023-12-20",
      "entry_price": 2644.0,
      "exit_date": "2023-12-21",
      "exit_price": 2537.5,
      "position_type": "SHORT",
      "quantity": 100,
      "pnl": 10650,
      "entry_rci": -61.66666666666667,
      "entry_adx": 31.268076331510706,
      "signal_reason": "RCI-:SELL(strength=61.7, +DI=19.1, -DI=30.4)",
      "exit_reason": "利益目標額達成(10650円)"
    },
    {
      "entry_date": "2023-12-22",
      "entry_price": 2516.0,
      "exit_date": "2023-12-28",
      "exit_price": 2556.0,
      "position_type": "SHORT",
      "quantity": 100,
      "pnl": -4000,
      "entry_rci": -66.66666666666667,
      "entry_adx": 36.79808727983116,
      "signal_reason": "RCI-:SELL(strength=66.7, +DI=14.8, -DI=38.5)",
      "exit_reason": "RCI傾き利確(12.0度)"
    },
    {
      "entry_date": "2024-01-10",
      "entry_price": 2745.0,
      "exit_date": "2024-01-11",
      "exit_price": 2844.0,
      "position_type": "LONG",
      "quantity": 100,
      "pnl": 9900,
      "entry_rci": 96.66666666666667,
      "entry_adx": 37.41763514856033,
      "signal_reason": "RCI+:BUY(strength=96.7, +DI=30.0, -DI=23.2, +DI/-DI=1.30 >= 1.20)",
      "exit_reason": "利益目標額達成(9900円)"
    },
    {
      "entry_date": "2024-01-12",
      "entry_price": 2837.0,
      "exit_date": "2024-01-18",
      "exit_price": 2931.5,
      "position_type": "LONG",
      "quantity": 100,
      "pnl": 9450,
      "entry_rci": 95.0,
      "entry_adx": 37.87762490504931,
      "signal_reason": "RCI+:BUY(strength=95.0, +DI=36.9, -DI=19.4, +DI/-DI=1.90 >= 1.20)",
      "exit_reason": "利益目標額達成(9450円)"
    },
    {
      "entry_date": "2024-01-19",
      "entry_price": 2962.0,
      "exit_date": "2024-01-26",
      "exit_price": 2892.5,
      "position_type": "LONG",
      "quantity": 100,
      "pnl": -6950,
      "entry_rci": 98.33333333333333,
      "entry_adx": 50.52050139936601,
      "signal_reason": "RCI+:BUY(strength=98.3, +DI=37.3, -DI=16.1, +DI/-DI=2.31 >= 1.20)",
      "exit_reason": "RCI傾き利確(-31.5度)"
    },
    {
      "entry_date": "2024-02-07",
      "entry_price": 3260.0,
      "exit_date": "2024-02-08",
      "exit_price": 3350.0,
      "position_type": "LONG",
      "quantity": 100,
      "pnl": 9000,
      "entry_rci": 68.33333333333333,
      "entry_adx": 67.80390735880883,
      "signal_reason": "RCI+:BUY(strength=68.3, +DI=55.5, -DI=5.4, +DI/-DI=10.35 >= 1.20)",
      "exit_reason": "利益目標額達成(9000円)"
    },
    {
      "entry_date": "2024-02-09",
      "entry_price": 3323.0,
      "exit_date": "2024-02-13",
      "exit_price": 3456.0,
      "position_type": "LONG",
      "quantity": 100,
      "pnl": 13300,
      "entry_rci": 80.0,
      "entry_adx": 63.85333988625269,
      "signal_reason": "RCI+:BUY(strength=80.0, +DI=48.9, -DI=4.3, +DI/-DI=11.25 >= 1.20)",
      "exit_reason": "利益目標額達成(13300円)"
    },
    {
      "entry_date": "2024-02-14",
      "entry_price": 3385.0,
      "exit_date": "2024-02-21",
      "exit_price": 3429.0,
      "position_type": "LONG",
      "quantity": 100,
      "pnl": 4400,
      "entry_rci": 96.66666666666667,
      "entry_adx": 60.611249886934914,
      "signal_reason": "RCI+:BUY(strength=96.7, +DI=47.3, -DI=3.3, +DI/-DI=14.17 >= 1.20)",
      "exit_reason": "RCI傾き利確(-12.0度)"
    },
    {
      "entry_date": "2024-02-22",
      "entry_price": 3521.0,
      "exit_date": "2024-02-27",
      "exit_price": 3582.0,
      "position_type": "LONG",
      "quantity": 100,
      "pnl": 6100,
      "entry_rci": 58.33333333333333,
      "entry_adx": 72.3685180105941,
      "signal_reason": "RCI+:BUY(strength=58.3, +DI=40.9, -DI=6.2, +DI/-DI=6.64 >= 1.20)",
      "exit_reason": "利益目標額達成(6100円)"
    },
    {
      "entry_date": "2024-02-28",
      "entry_price": 3570.0,
      "exit_date": "2024-02-29",
      "exit_price": 3621.0,
      "position_type": "LONG",
      "quantity": 100,
      "pnl": 5100,
      "entry_rci": 93.33333333333333,
      "entry_adx": 80.54925958256375,
      "signal_reason": "RCI+:BUY(strength=93.3, +DI=39.8, -DI=8.1, +DI/-DI=4.93 >= 1.20)",
      "exit_reason": "利益目標額達成(5100円)"
    },
    {
      "entry_date": "2024-03-01",
      "entry_price": 3680.0,
      "exit_date": "2024-03-06",
      "exit_price": 3769.0,
      "position_type": "LONG",
      "quantity": 100,
      "pnl": 8900,
      "entry_rci": 93.33333333333333,
      "entry_adx": 80.82223382414209,
      "signal_reason": "RCI+:BUY(strength=93.3, +DI=41.2, -DI=7.2, +DI/-DI=5.70 >= 1.20)",
      "exit_reason": "利益目標額達成(8900円)"
    },
    {
      "entry_date": "2024-03-07",
      "entry_price": 3660.0,
      "exit_date": "2024-03-08",
      "exit_price": 3610.0,
      "position_type": "LONG",
      "quantity": 100,
      "pnl": -5000,
      "entry_rci": 80.0,
      "entry_adx": 79.2366231273564,
      "signal_reason": "RCI+:BUY(strength=80.0, +DI=35.3, -DI=8.8, +DI/-DI=4.03 >= 1.20)",
      "exit_reason": "RCI傾き利確(-31.5度)"
    },
    {
      "entry_date": "2024-03-22",
      "entry_price": 3872.0,
      "exit_date": "2024-03-28",
      "exit_price": 3806.0,
      "position_type": "LONG",
      "quantity": 100,
      "pnl": -6600,
      "entry_rci": 78.33333333333333,
      "entry_adx": 30.3258510538638,
      "signal_reason": "RCI+:BUY(strength=78.3, +DI=43.6, -DI=13.4, +DI/-DI=3.25 >= 1.20)",
      "exit_reason": "RCI傾き利確(-15.0度)"
    },
    {
      "entry_date": "2024-06-04",
      "entry_price": 3298.0,
      "exit_date": "2024-06-05",
      "exit_price": 3218.0,
      "position_type": "SHORT",
      "quantity": 100,
      "pnl": 8000,
      "entry_rci": -70.0,
      "entry_adx": 37.67160254448822,
      "signal_reason": "RCI-:SELL(strength=70.0, +DI=13.9, -DI=28.2)",
      "exit_reason": "利益目標額達成(8000円)"
    },
    {
      "entry_date": "2024-06-06",
      "entry_price": 3273.0,
      "exit_date": "2024-06-07",
      "exit_price": 3219.0,
      "position_type": "SHORT",
      "quantity": 100,
      "pnl": 5400,
      "entry_rci": -89.99999999999999,
      "entry_adx": 37.56114141191065,
      "signal_reason": "RCI-:SELL(strength=90.0, +DI=15.5, -DI=31.6)",
      "exit_reason": "利益目標額達成(5400円)"
    },
    {
      "entry_date": "2024-06-10",
      "entry_price": 3272.0,
      "exit_date": "2024-06-12",
      "exit_price": 3209.0,
      "position_type": "SHORT",
      "quantity": 100,
      "pnl": 6300,
      "entry_rci": -80.0,
      "entry_adx": 41.45754149081538,
      "signal_reason": "RCI-:SELL(strength=80.0, +DI=16.0, -DI=32.0)",
      "exit_reason": "利益目標額達成(6300円)"
    },
    {
      "entry_date": "2024-06-13",
      "entry_price": 3128.0,
      "exit_date": "2024-06-17",
      "exit_price": 3036.0,
      "position_type": "SHORT",
      "quantity": 100,
      "pnl": 9200,
      "entry_rci": -78.33333333333334,
      "entry_adx": 38.85359451220729,
      "signal_reason": "RCI-:SELL(strength=78.3, +DI=12.3, -DI=37.9)",
      "exit_reason": "利益目標額達成(9200円)"
    },
    {
      "entry_date": "2024-06-18",
      "entry_price": 3052.0,
      "exit_date": "2024-06-21",
      "exit_price": 3074.0,
      "position_type": "SHORT",
      "quantity": 100,
      "pnl": -2200,
      "entry_rci": -93.33333333333333,
      "entry_adx": 41.87208021590538,
      "signal_reason": "RCI-:SELL(strength=93.3, +DI=12.7, -DI=41.1)",
      "exit_reason": "RCI傾き利確(10.5度)"
    },
    {
      "entry_date": "2024-07-02",
      "entry_price": 3333.0,
      "exit_date": "2024-07-04",
      "exit_price": 3391.0,
      "position_type": "LONG",
      "quantity": 100,
      "pnl": 5800,
      "entry_rci": 78.33333333333333,
      "entry_adx": 31.120330230269655,
      "signal_reason": "RCI+:BUY(strength=78.3, +DI=25.6, -DI=21.2, +DI/-DI=1.21 >= 1.20)",
      "exit_reason": "利益目標額達成(5800円)"
    },
    {
      "entry_date": "2024-07-05",
      "entry_price": 3319.0,
      "exit_date": "2024-07-09",
      "exit_price": 3270.0,
      "position_type": "LONG",
      "quantity": 100,
      "pnl": -4900,
      "entry_rci": 68.33333333333333,
      "entry_adx": 32.87127578085672,
      "signal_reason": "RCI+:BUY(strength=68.3, +DI=25.2, -DI=20.9, +DI/-DI=1.21 >= 1.20)",
      "exit_reason": "RCI傾き利確(-40.5度)"
    },
    {
      "entry_date": "2024-07-12",
      "entry_price": 3274.0,
      "exit_date": "2024-07-18",
      "exit_price": 3141.0,
      "position_type": "SHORT",
      "quantity": 100,
      "pnl": 13300,
      "entry_rci": -81.66666666666667,
      "entry_adx": 33.51855926964943,
      "signal_reason": "RCI-:SELL(strength=81.7, +DI=22.8, -DI=28.0)",
      "exit_reason": "利益目標額達成(13300円)"
    },
    {
      "entry_date": "2024-07-19",
      "entry_price": 3133.0,
      "exit_date": "2024-07-25",
      "exit_price": 3020.0,
      "position_type": "SHORT",
      "quantity": 100,
      "pnl": 11300,
      "entry_rci": -86.66666666666667,
      "entry_adx": 37.84195003553394,
      "signal_reason": "RCI-:SELL(strength=86.7, +DI=19.5, -DI=36.2)",
      "exit_reason": "利益目標額達成(11300円)"
    },
    {
      "entry_date": "2024-07-26",
      "entry_price": 2909.0,
      "exit_date": "2024-08-01",
      "exit_price": 2699.0,
      "position_type": "SHORT",
      "quantity": 100,
      "pnl": 21000,
      "entry_rci": -95.0,
      "entry_adx": 40.38701393090496,
      "signal_reason": "RCI-:SELL(strength=95.0, +DI=20.4, -DI=37.6)",
      "exit_reason": "利益目標額達成(21000円)"
    },
    {
      "entry_date": "2024-08-02",
      "entry_price": 2585.0,
      "exit_date": "2024-08-05",
      "exit_price": 2232.0,
      "position_type": "SHORT",
      "quantity": 100,
      "pnl": 35300,
      "entry_rci": -88.33333333333333,
      "entry_adx": 46.5173348961964,
      "signal_reason": "RCI-:SELL(strength=88.3, +DI=12.3, -DI=49.2)",
      "exit_reason": "利益目標額達成(35300円)"
    },
    {
      "entry_date": "2024-08-06",
      "entry_price": 2518.0,
      "exit_date": "2024-08-08",
      "exit_price": 2451.0,
      "position_type": "SHORT",
      "quantity": 100,
      "pnl": 6700,
      "entry_rci": -86.66666666666667,
      "entry_adx": 56.97760789205201,
      "signal_reason": "RCI-:SELL(strength=86.7, +DI=10.8, -DI=49.9)",
      "exit_reason": "利益目標額達成(6700円)"
    },
    {
      "entry_date": "2024-08-09",
      "entry_price": 2447.5,
      "exit_date": "2024-08-13",
      "exit_price": 2529.0,
      "position_type": "SHORT",
      "quantity": 100,
      "pnl": -8150,
      "entry_rci": -83.33333333333333,
      "entry_adx": 61.80490342219319,
      "signal_reason": "RCI-:SELL(strength=83.3, +DI=10.8, -DI=42.4)",
      "exit_reason": "RCI傾き利確(22.5度)"
    },
    {
      "entry_date": "2024-09-11",
      "entry_price": 2422.0,
      "exit_date": "2024-09-18",
      "exit_price": 2485.0,
      "position_type": "SHORT",
      "quantity": 100,
      "pnl": -6300,
      "entry_rci": -95.0,
      "entry_adx": 30.188285289588766,
      "signal_reason": "RCI-:SELL(strength=95.0, +DI=18.8, -DI=43.2)",
      "exit_reason": "RCI傾き利確(10.5度)"
    },
    {
      "entry_date": "2024-12-24",
      "entry_price": 2835.0,
      "exit_date": "2024-12-25",
      "exit_price": 2964.5,
      "position_type": "LONG",
      "quantity": 100,
      "pnl": 12950,
      "entry_rci": 80.0,
      "entry_adx": 30.387075120030197,
      "signal_reason": "RCI+:BUY(strength=80.0, +DI=31.5, -DI=17.2, +DI/-DI=1.83 >= 1.20)",
      "exit_reason": "利益目標額達成(12950円)"
    },
    {
      "entry_date": "2024-12-26",
      "entry_price": 3142.0,
      "exit_date": "2025-01-06",
      "exit_price": 3011.0,
      "position_type": "LONG",
      "quantity": 100,
      "pnl": -13100,
      "entry_rci": 95.0,
      "entry_adx": 37.34694383592144,
      "signal_reason": "RCI+:BUY(strength=95.0, +DI=50.5, -DI=10.8, +DI/-DI=4.66 >= 1.20)",
      "exit_reason": "stop_loss"
    },
    {
      "entry_date": "2025-01-07",
      "entry_price": 3052.0,
      "exit_date": "2025-01-08",
      "exit_price": 3073.0,
      "position_type": "LONG",
      "quantity": 100,
      "pnl": 2100,
      "entry_rci": 71.66666666666667,
      "entry_adx": 49.62352716011168,
      "signal_reason": "RCI+:BUY(strength=71.7, +DI=39.0, -DI=20.2, +DI/-DI=1.93 >= 1.20)",
      "exit_reason": "RCI傾き利確(-18.0度)"
    },
    {
      "entry_date": "2025-01-16",
      "entry_price": 2837.0,
      "exit_date": "2025-01-22",
      "exit_price": 2915.5,
      "position_type": "SHORT",
      "quantity": 100,
      "pnl": -7850,
      "entry_rci": -93.33333333333333,
      "entry_adx": 47.098835807016464,
      "signal_reason": "RCI-:SELL(strength=93.3, +DI=28.0, -DI=29.2)",
      "exit_reason": "トレーリングストップ(4.0%)"
    },
    {
      "entry_date": "2025-04-24",
      "entry_price": 2657.5,
      "exit_date": "2025-04-28",
      "exit_price": 2786.5,
      "position_type": "LONG",
      "quantity": 100,
      "pnl": 12900,
      "entry_rci": 53.333333333333336,
      "entry_adx": 30.868801467928105,
      "signal_reason": "RCI+:BUY(strength=53.3, +DI=35.5, -DI=27.9, +DI/-DI=1.27 >= 1.20)",
      "exit_reason": "利益目標額達成(12900円)"
    },
    {
      "entry_date": "2025-05-02",
      "entry_price": 2780.0,
      "exit_date": "2025-05-07",
      "exit_price": 2706.0,
      "position_type": "LONG",
      "quantity": 100,
      "pnl": -7400,
      "entry_rci": 88.33333333333333,
      "entry_adx": 31.243017150974335,
      "signal_reason": "RCI+:BUY(strength=88.3, +DI=36.5, -DI=25.9, +DI/-DI=1.41 >= 1.20)",
      "exit_reason": "RCI傾き利確(-13.5度)"
    },
    {
      "entry_date": "2025-06-26",
      "entry_price": 2456.5,
      "exit_date": "2025-06-27",
      "exit_price": 2527.0,
      "position_type": "SHORT",
      "quantity": 100,
      "pnl": -7050,
      "entry_rci": -95.0,
      "entry_adx": 30.368033237607616,
      "signal_reason": "RCI-:SELL(strength=95.0, +DI=18.7, -DI=32.8)",
      "exit_reason": "RCI傾き利確(28.5度)"
    },
    {
      "entry_date": "2025-06-30",
      "entry_price": 2493.0,
      "exit_date": "2025-07-03",
      "exit_price": 2511.5,
      "position_type": "SHORT",
      "quantity": 100,
      "pnl": -1850,
      "entry_rci": -50.0,
      "entry_adx": 32.35081882361114,
      "signal_reason": "RCI-:SELL(strength=50.0, +DI=26.4, -DI=28.0)",
      "exit_reason": "RCI傾き利確(40.5度)"
    },
    {
      "entry_date": "2025-07-28",
      "entry_price": 2805.0,
      "exit_date": "2025-07-30",
      "exit_price": 2743.5,
      "position_type": "LONG",
      "quantity": 100,
      "pnl": -6150,
      "entry_rci": 56.666666666666664,
      "entry_adx": 34.88495089750938,
      "signal_reason": "RCI+:BUY(strength=56.7, +DI=45.7, -DI=16.4, +DI/-DI=2.79 >= 1.20)",
      "exit_reason": "RCI傾き利確(-16.5度)"
    },
    {
      "entry_date": "2025-08-13",
      "entry_price": 2875.0,
      "exit_date": "2025-08-19",
      "exit_price": 2925.0,
      "position_type": "LONG",
      "quantity": 100,
      "pnl": 5000,
      "entry_rci": 65.0,
      "entry_adx": 37.11412657532885,
      "signal_reason": "RCI+:BUY(strength=65.0, +DI=41.2, -DI=17.3, +DI/-DI=2.38 >= 1.20)",
      "exit_reason": "利益目標額達成(5000円)"
    },
    {
      "entry_date": "2025-09-09",
      "entry_price": 2949.0,
      "exit_date": "2025-09-11",
      "exit_price": 2886.5,
      "position_type": "LONG",
      "quantity": 100,
      "pnl": -6250,
      "entry_rci": 55.00000000000001,
      "entry_adx": 34.59301065719595,
      "signal_reason": "RCI+:BUY(strength=55.0, +DI=35.4, -DI=15.3, +DI/-DI=2.32 >= 1.20)",
      "exit_reason": "RCI傾き利確(-13.5度)"
    },
    {
      "entry_date": "2025-09-25",
      "entry_price": 2961.5,
      "exit_date": "2025-09-29",
      "exit_price": 2870.0,
      "position_type": "LONG",
      "quantity": 100,
      "pnl": -9150,
      "entry_rci": 63.33333333333333,
      "entry_adx": 30.116260046667428,
      "signal_reason": "RCI+:BUY(strength=63.3, +DI=29.9, -DI=12.5, +DI/-DI=2.40 >= 1.20)",
      "exit_reason": "RCI傾き利確(-54.0度)"
    }
  ],
  "summary": {
    "total_trades": 101,
    "total_pnl": 40320,
    "long_trades": 61,
    "short_trades": 40,
    "winning_trades": 40,
    "losing_trades": 61
  }
}